brainfuck/__init__.py
brainfuck/brainfuck.py
brain_fuck_interpreter_cmdl-1.1.1.dist-info/METADATA
brain_fuck_interpreter_cmdl-1.1.1.dist-info/WHEEL
brain_fuck_interpreter_cmdl-1.1.1.dist-info/entry_points.txt
brain_fuck_interpreter_cmdl-1.1.1.dist-info/top_level.txt
brain_fuck_interpreter_cmdl-1.1.1.dist-info/RECORD
