Metadata-Version: 2.1
Name: brain-fuck-interpreter-cmdl
Version: 1.1.1
Summary: BrainFuck Interpreter
Home-page: UNKNOWN
Author: Cargo
License: UNKNOWN
Platform: UNKNOWN
Requires-Dist: click
